mill/__init__.py
mill/consts.py
millheater-0.14.1.dist-info/licenses/LICENSE
millheater-0.14.1.dist-info/METADATA
millheater-0.14.1.dist-info/WHEEL
millheater-0.14.1.dist-info/top_level.txt
millheater-0.14.1.dist-info/RECORD
